theia/__init__.py
theia/data_gen/__init__.py
theia/data_gen/tiled.py
theia/models/__init__.py
theia/models/base.py
theia/models/lasso.py
theia/models/neural.py
theia/models/transformer.py
theia/utils/__init__.py
theia/utils/constants.py
theia_py-0.1.2.dist-info/LICENSE
theia_py-0.1.2.dist-info/METADATA
theia_py-0.1.2.dist-info/WHEEL
theia_py-0.1.2.dist-info/RECORD
