Metadata-Version: 2.1
Name: theia-py
Version: 0.1.2
Summary: Theia: Bleed-Through Correction in Fluorescent Microscopy Images
License: MIT
Author: Najib Ishaq
Author-email: najib.ishaq@nih.gov
Requires-Python: >=3.9, !=2.7.*, !=3.0.*, !=3.1.*, !=3.2.*, !=3.3.*, !=3.4.*, !=3.5.*, !=3.6.*, !=3.7.*, !=3.8.*, !=3.12.*
Classifier: License :: OSI Approved :: MIT License
Classifier: Programming Language :: Python :: 3
Classifier: Programming Language :: Python :: 3.9
Classifier: Programming Language :: Python :: 3.10
Classifier: Programming Language :: Python :: 3.11
Requires-Dist: numpy (>=1.23.2,<2.0.0)
Requires-Dist: scikit-learn (>=1.2.2,<2.0.0)
Requires-Dist: scipy (>=1.9.0,<2.0.0)
Requires-Dist: tensorflow (>=2.13.0,<3.0.0)
